pydatanet/__init__.py
pydatanet/data.py
pydatanet/client/__init__.py
pydatanet/server/__init__.py
pydatanet/server/client/__init__.py
pydatanet-0.1.2.dist-info/LICENSE
pydatanet-0.1.2.dist-info/METADATA
pydatanet-0.1.2.dist-info/WHEEL
pydatanet-0.1.2.dist-info/top_level.txt
pydatanet-0.1.2.dist-info/RECORD
