Metadata-Version: 2.1
Name: pydatanet
Version: 0.1.2
Summary: A fancy networking library which supports both the protocols and makes it hard to shoot yourself in the foot.
Home-page: https://github.com/xTrayambak/pysyn
Author: xTrayambak
Author-email: xtrayambak@gmail.com
License: UNKNOWN
Project-URL: Bug Tracker, https://github.com/xTrayambak/pysyn/issues
Platform: UNKNOWN
Classifier: Programming Language :: Python :: 3
Classifier: License :: OSI Approved :: MIT License
Classifier: Operating System :: OS Independent
Requires-Python: >=3.8
License-File: LICENSE
